botlabspy/API.py
botlabspy/__init__.py
Botlabs.py-1.0.4.dist-info/LICENSE
Botlabs.py-1.0.4.dist-info/METADATA
Botlabs.py-1.0.4.dist-info/WHEEL
Botlabs.py-1.0.4.dist-info/top_level.txt
Botlabs.py-1.0.4.dist-info/RECORD
