Metadata-Version: 2.1
Name: Botlabs.py
Version: 1.0.4
Summary: A simple API wrapper for discordbotlabs.org
Home-page: https://github.com/pjotr07740/botlabs.py
Author: Pjotr
Author-email: pjotrlspdfr@outlook.com
License: UNKNOWN
Platform: UNKNOWN
Classifier: Programming Language :: Python :: 3
Classifier: License :: OSI Approved :: Apache Software License
Classifier: Operating System :: OS Independent
Requires-Python: >=3.6
